PyQuantimClient/__init__.py
PyQuantimClient/alm.py
PyQuantimClient/api.py
PyQuantimClient/benchmarks.py
PyQuantimClient/bi.py
PyQuantimClient/credit.py
PyQuantimClient/data.py
PyQuantimClient/energy.py
PyQuantimClient/mstar.py
PyQuantimClient/performance.py
PyQuantimClient/portfolios.py
PyQuantimClient/preprocess_co.py
PyQuantimClient/private_debt.py
PyQuantimClient/product.py
PyQuantimClient/returns.py
PyQuantimClient/risk.py
PyQuantimClient/utils.py
pyquantimclient-2.0.63.dist-info/METADATA
pyquantimclient-2.0.63.dist-info/WHEEL
pyquantimclient-2.0.63.dist-info/top_level.txt
pyquantimclient-2.0.63.dist-info/RECORD
