Metadata-Version: 2.4
Name: PyQuantimClient
Version: 2.0.63
Summary: Python client to access quantIM services
Author: Daniel Velasquez
Author-email: daniel.velasquez@sura-im.com
Classifier: Programming Language :: Python :: 3
Classifier: License :: OSI Approved :: MIT License
Classifier: Operating System :: OS Independent
Requires-Python: >=3.7
Dynamic: author
Dynamic: author-email
Dynamic: classifier
Dynamic: requires-python
Dynamic: summary
